[
  {
    "tender_id": "UA-2026-04-29-008605-a",
    "enabled": true,
    "notes": "Комунальне некомерційне підприємство \"Центральна районна лікарня Калуської міської  ради Івано-Франківської області\" — Послуги з постачання та налаштування програмного забезпечення лабораторної інфор…"
  },
  {
    "tender_id": "UA-2026-04-22-013036-a",
    "enabled": true,
    "notes": "Комунальне некомерційне підприємство \"Хмельницький  обласний заклад з надання психіатричної  допомоги\" Хмельницької обласної ради — Послуги з постачання та налаштування програмного забезпечення лабор…"
  },
  {
    "tender_id": "UA-2026-04-16-005830-a",
    "enabled": true,
    "notes": "Комунальне некомерційне підприємство \"Коростишівська ЦРЛ ім.Д.І.Потєхіна\" — 72260000-5 - Послуги, пов’язані з програмним забезпеченням"
  },
  {
    "tender_id": "UA-2026-04-30-010542-a",
    "enabled": true,
    "notes": "КОМУНАЛЬНЕ ПІДПРИЄМСТВО \"РІВНЕНСЬКА ОБЛАСНА КЛІНІЧНА ЛІКАРНЯ ІМЕНІ ЮРІЯ СЕМЕНЮКА\" РІВНЕНСЬКОЇ ОБЛАСНОЇ РАДИ — Консалтингові послуги з підготовки медичної лабораторії до акредитації згідно зі стандарт…"
  },
  {
    "tender_id": "UA-2026-05-01-012131-a",
    "enabled": true,
    "notes": "військова частина А1356 — Детектори та аналізатори"
  },
  {
    "tender_id": "UA-2026-05-07-015343-a",
    "enabled": true,
    "notes": "МИРОНІВСЬКА МІСЬКА РАДА — Розроблення комплексного плану просторового розвитку території Миронівської міської територіальної громади Обухівського району Київської області, концепції інтегрованого роз…"
  }
]
